mediascan/__init__.py
mediascan/__main__.py
mediascan/config.py
mediascan/interpreter.py
mediascan/logging.py
mediascan/mediascan.py
mediascan-0.1.7.dist-info/LICENSE
mediascan-0.1.7.dist-info/METADATA
mediascan-0.1.7.dist-info/WHEEL
mediascan-0.1.7.dist-info/entry_points.txt
mediascan-0.1.7.dist-info/top_level.txt
mediascan-0.1.7.dist-info/RECORD
