Metadata-Version: 2.1
Name: mediascan
Version: 0.1.7
Summary: A Python package for scanning and organizing media files.
Home-page: http://github.com/philiporange/mediascan
Author: Philip Orange
Author-email: git@philiporange.com
License: UNKNOWN
Platform: UNKNOWN
Classifier: Development Status :: 3 - Alpha
Classifier: Intended Audience :: Developers
Classifier: License :: CC0 1.0 Universal (CC0 1.0) Public Domain Dedication
Classifier: Operating System :: OS Independent
Classifier: Programming Language :: Python :: 3
Classifier: Programming Language :: Python :: 3.7
Classifier: Programming Language :: Python :: 3.8
Classifier: Programming Language :: Python :: 3.9
Classifier: Programming Language :: Python :: 3.10
Requires-Python: >=3.7
License-File: LICENSE
Requires-Dist: appdirs
Requires-Dist: loguru
Requires-Dist: python-dotenv
Requires-Dist: pyyaml
Requires-Dist: redislite
Requires-Dist: requests
